packety/__init__.py
packety/client.py
packety/server.py
packety/conntypes/__init__.py
packety/conntypes/eventbased.py
packety/packets/__init__.py
packety/packets/base.py
packety/packets/meta_schema.py
packety/packets/schema.py
packety/packets/validate.py
packety-0.2.2.dist-info/DESCRIPTION.rst
packety-0.2.2.dist-info/METADATA
packety-0.2.2.dist-info/RECORD
packety-0.2.2.dist-info/WHEEL
packety-0.2.2.dist-info/metadata.json
packety-0.2.2.dist-info/top_level.txt
