Metadata-Version: 2.0
Name: packety
Version: 0.2.2
Summary: Simple packet based networking, with a side of async
Home-page: https://github.com/mincrmatt12/packety
Author: mincrmatt12
Author-email: UNKNOWN
License: UNKNOWN
Keywords: networking packet async
Platform: UNKNOWN
Requires-Dist: gevent
Requires-Dist: six
